superduper_chromadb/__init__.py
superduper_chromadb/chromadb.py
superduper_chromadb-0.10.0.dist-info/licenses/LICENSE
superduper_chromadb-0.10.0.dist-info/METADATA
superduper_chromadb-0.10.0.dist-info/WHEEL
superduper_chromadb-0.10.0.dist-info/top_level.txt
superduper_chromadb-0.10.0.dist-info/RECORD
