Metadata-Version: 2.4
Name: superduper-chromadb
Version: 0.10.0
Summary: SuperDuper Lance is a Python library that provides a high-level API for working with Lance vector search database.
Maintainer-email: "superduper.io, Inc." <opensource@superduper.io>
License: 
Project-URL: homepage, https://superduper.io
Project-URL: documentation, https://docs.superduper.io/docs/intro
Project-URL: source, https://github.com/superduper-io/superduper
Keywords: databases,mongodb,data-science,machine-learning,mlops,vector-database,ai
Requires-Python: >=3.10
License-File: LICENSE
Requires-Dist: chromadb
Dynamic: license-file
